[
  {
    "title": "Программирование",
    "date": "21.04.2022",
    "preview": "RuGPT3: Программирование"
  },
  {
    "title": "Машины",
    "date": "21.04.2022",
    "preview": "RuGPT3: Машины с военной тематикой:"
  },
  {
    "title": "Кулинария",
    "date": "21.04.2022",
    "preview": "RuGPT3: Кулинария, как–то)"
  },
  {
    "title": "Компьютеры",
    "date": "21.04.2022",
    "preview": "RuGPT3: Компьютеры"
  },
  {
    "title": "Одежда",
    "date": "21.04.2022",
    "preview": "RuGPT3: Одежда на сезон весна лето 2012 "
  }
]